{"cameraMode":{"drawMode":0,"name":"Shaded","section":"Shading Mode"},"sceneLighting":true,"audioPlay":false,"sceneViewState":{"m_AlwaysRefresh":false,"showFog":true,"showSkybox":true,"showFlares":true,"showImageEffects":true,"showParticleSystems":true,"showVisualEffectGraphs":true,"m_FxEnabled":true},"in2DMode":false,"pivot":{"x":-14.476704597473145,"y":3.6881299018859865,"z":-34.60993957519531},"rotation":{"x":0.013509872369468212,"y":0.004556555766612291,"z":-0.00009299663361161947,"w":1.0000083446502686},"size":1.4919264316558838,"orthographic":false}